pyDSV/__init__.py
pyDSV/csvLoader.py
pyDSV/dsvTransformer.py
tests/__init__.py
tests/test_csvLoader.py
tests/test_dsvTransformer.py
pyDSV-0.1.0.dist-info/LICENSE
pyDSV-0.1.0.dist-info/METADATA
pyDSV-0.1.0.dist-info/WHEEL
pyDSV-0.1.0.dist-info/top_level.txt
pyDSV-0.1.0.dist-info/RECORD
