Metadata-Version: 2.1
Name: pyDSV
Version: 0.1.0
Summary: A Python tool for converting CSV data into RDF using the DSV ontology
Home-page: UNKNOWN
Author: Margherita Martorana
Author-email: m.martorana@vu.nl
License: MIT
Platform: UNKNOWN
Classifier: Programming Language :: Python :: 3
Classifier: Operating System :: OS Independent
License-File: LICENSE
Requires-Dist: pandas
Requires-Dist: rdflib
